obsah/__init__.py
obsah/__main__.py
obsah/constraints.py
obsah/data_types.py
obsah/py.typed
obsah/data/.keep
obsah-1.6.0.dist-info/licenses/LICENSE
obsah-1.6.0.dist-info/METADATA
obsah-1.6.0.dist-info/WHEEL
obsah-1.6.0.dist-info/entry_points.txt
obsah-1.6.0.dist-info/top_level.txt
obsah-1.6.0.dist-info/RECORD
