Metadata-Version: 2.4
Name: obsah
Version: 1.6.0
Summary: packaging wrapper using ansible
Home-page: https://github.com/theforeman/obsah
Author: The Foreman Project
Author-email: foreman-dev@googlegroups.com
License: GPL-2.0-only
Project-URL: Documentation, https://obsah.readthedocs.io/en/latest/
Project-URL: Source, https://github.com/theforeman/obsah
Keywords: ansible foreman packaging koji brew mock
Classifier: Development Status :: 5 - Production/Stable
Classifier: Intended Audience :: Developers
Classifier: Topic :: Software Development :: Build Tools
Classifier: Programming Language :: Python :: 3
Classifier: Programming Language :: Python :: 3.9
Classifier: Programming Language :: Python :: 3.10
Classifier: Programming Language :: Python :: 3.11
Classifier: Programming Language :: Python :: 3.12
Classifier: Programming Language :: Python :: 3.13
Requires-Python: >=3.9, <4
License-File: LICENSE
Requires-Dist: ansible-core
Provides-Extra: argcomplete
Requires-Dist: argcomplete; extra == "argcomplete"
Dynamic: author
Dynamic: author-email
Dynamic: classifier
Dynamic: description
Dynamic: description-content-type
Dynamic: home-page
Dynamic: keywords
Dynamic: license
Dynamic: license-file
Dynamic: project-url
Dynamic: provides-extra
Dynamic: requires-dist
Dynamic: requires-python
Dynamic: summary
